SDP18py/Generate_initial_solution.py
SDP18py/MOSHCR.py
SDP18py/MO_fitting_func_calc.py
SDP18py/NSGAII.py
SDP18py/TAMOCO.py
SDP18py/UMOSA.py
SDP18py/__init__.py
SDP18py/find_legal_neighbors.py
SDP18py/generate_mock_schedule.py
SDP18py/generate_surg_to_schedule.py
SDP18py/genetic_algo_functions.py
SDP18py/login_page.py
SDP18py/plot_pareto_front.py
SDP18py/read_MAS.py
SDP18py/read_csv.py
SDP18py/read_toschedule.py
SDP18py/swapper.py
SDP18py/view_timetable1.py
SDP18py-0.3.1.dist-info/LICENCE.txt
SDP18py-0.3.1.dist-info/METADATA
SDP18py-0.3.1.dist-info/WHEEL
SDP18py-0.3.1.dist-info/top_level.txt
SDP18py-0.3.1.dist-info/RECORD
